README.md
setup.py
pyOSC3/OSC2.py
pyOSC3/OSC3.py
pyOSC3/__init__.py
pyOSC3.egg-info/PKG-INFO
pyOSC3.egg-info/SOURCES.txt
pyOSC3.egg-info/dependency_links.txt
pyOSC3.egg-info/top_level.txt