Metadata-Version: 1.0
Name: pyOSC3
Version: 1.1
Summary: pyOSC updated for Python 3
Home-page: http://foxdot.org/
Author: Ryan Kirkbride
Author-email: ryan@foxdot.org
License: UNKNOWN
Platform: UNKNOWN
